phone_db/__init__.py
phone_db/model.py
phone_db/phone.db
phone_db/test.py
phone_db-1.0.3.dist-info/LICENSE
phone_db-1.0.3.dist-info/METADATA
phone_db-1.0.3.dist-info/WHEEL
phone_db-1.0.3.dist-info/top_level.txt
phone_db-1.0.3.dist-info/RECORD
