Metadata-Version: 2.1
Name: phone-db
Version: 1.0.3
Summary: 手机号码SQLite数据库
Home-page: https://github.com/lalala223/phone-db
Author: lalala223
Author-email: hi@lalala.ink
License: MIT
Platform: UNKNOWN
Classifier: License :: OSI Approved :: MIT License
Classifier: Programming Language :: Python
Classifier: Intended Audience :: Developers
Classifier: Operating System :: OS Independent
Requires-Dist: sqlalchemy
